examples/__init__.py
examples/basic_usage.py
wallhaven_crawler-0.1.2.dist-info/METADATA
wallhaven_crawler-0.1.2.dist-info/WHEEL
wallhaven_crawler-0.1.2.dist-info/top_level.txt
wallhaven_crawler-0.1.2.dist-info/RECORD
