Metadata-Version: 2.1
Name: wallhaven-crawler
Version: 0.1.2
Summary: A powerful crawler for Wallhaven website
Home-page: https://github.com/KyrieMU/wallhaven-crawler
Author: kyriechen
Author-email: your.email@example.com
Classifier: Programming Language :: Python :: 3
Classifier: License :: OSI Approved :: MIT License
Classifier: Operating System :: OS Independent
Requires-Python: >=3.6
Requires-Dist: requests
Requires-Dist: beautifulsoup4
